{
    "id": "",
    "title": "",
    "url": "https://www.reuters.com/markets/us/futures-inch-up-with-payrolls-data-powells-remarks-tap-2025-03-07/",
    "source": "reuters",
    "category": "business",
    "published_date": "2025-03-07T18:15:52Z",
    "scraped_date": "2025-03-07T20:58:01.750231",
    "content": "March 7 (Reuters) - Wall Street's main indexes traded off session lows on Friday as investors assessed comments from Fed Chair Jerome Powell amid economic uncertainty fanned by the Trump administration's tariff policies.\nPowell said the Federal Reserve will take a cautious approach to monetary policy easing, adding that the economy currently \"continues to be in a good place\".\n\"But they (the Fed) may not be able to do anything in terms of lowering rates because while the economy is slowing, inflation is a problem,\" said Oliver Pursche, senior vice president at Wealthspire Advisors.\nAt 01:00 p.m. ET the Dow Jones Industrial Average (.DJI)\n, opens new tab\nfell 71.45 points, or 0.17%, to 42,507.63, the S&P 500 (.SPX)\n, opens new tab\nlost 21.91 points, or 0.38%, to 5,716.61 and the Nasdaq Composite (.IXIC)\n, opens new tab\nlost 104.92 points, or 0.58%, to 17,961.85.\nCyclical sectors such as consumer discretionary (.SPLRCD)\n, opens new tab\nfell 1.8%, while banks such as Wells Fargo (WFC.N)\n, opens new tab\nand Goldman Sachs (GS.N)\n, opens new tab\ndeclined, pushing the broader banks index (.SPXBK)\n, opens new tab\ndown 1.9%.\nMost megacaps also dropped. Meta (META.O)\n, opens new tab\nand Amazon.com (AMZN.O)\n, opens new tab\nfell more than 3% each.\nEarlier in the day, a Labor Department report showed job growth picked up in February from the previous month. However, unemployment ticked up to 4.1%, adding to worries about the economy's resilience.\nFollowing the data, traders revised their expectations of the first interest rate cut this year to June from May, according to data compiled by LSEG.\nAdding to the dour sentiment, brokerages Morgan Stanley and Goldman Sachs lowered their growth forecasts for the economy.\nEquities witnessed their most volatile week this year, with Wall Street's fear gauge (.VIX)\n, opens new tab\ntrading near levels not seen since mid-December, as traders tried to assess President Donald Trump's fluctuating trade policy.\nIn the previous session, the Nasdaq confirmed a 10% drop from its December all-time high, while the benchmark S&P 500 (.SPX)\n, opens new tab\nappeared to have reversed most of its gains since Trump's election victory.\nThe indexes, along with the blue-chip Dow (.DJI)\n, opens new tab\n, are on track for their biggest weekly drop since September. Equity funds witnessed the largest weekly outflow in four weeks in the week ended on March 5.\nTrump on Thursday offered a four-week reprieve on tariffs he imposed on imports from Canada and Mexico that fall under a free-trade pact, but the U.S. is still in a trade war with China. Additionally, reciprocal trade barriers and other duties are expected to take effect in the following weeks.\nHewlett Packard Enterprise (HPE.N)\n, opens new tab\nslumped 15.8% after saying its annual profit forecast would be hit by U.S. tariffs.\nCostco (COST.O)\n, opens new tab\nfell 7% after the retailer missed Street estimates on quarterly earnings as merchandise costs increased.\nBroadcom (AVGO.O)\n, opens new tab\n, on the other hand, rose 5.5% after the chipmaker assuaged investor worries about artificial intelligence infrastructure demand with a strong second-quarter forecast.\nDeclining issues outnumbered advancers for a 1.18-to-1 ratio on the NYSE and a 1.36-to-1 ratio on the Nasdaq.\nThe S&P 500 posted seven new 52-week highs and 13 new lows, while the Nasdaq Composite recorded 18 new highs and 140 new lows."
}